k2health/__init__.py
k2health/k2_health_rev2.py
k2health/pipeline.py
k2magic/__init__.py
k2magic/dataframe_db.py
k2magic/dataframe_db_exception.py
k2magic/k2_dataframe_db.py
k2magic/dialect/__init__.py
k2magic/dialect/calcite_dialect.py
k2magic/dialect/k2a_requests.py
k2magic/dialect/rdb_dialect.py
k2magic/handler/__init__.py
k2magic/handler/k2a_handler.py
k2magic/handler/nailgun_repo_data.py
k2magic-0.3.41.dist-info/METADATA
k2magic-0.3.41.dist-info/WHEEL
k2magic-0.3.41.dist-info/top_level.txt
k2magic-0.3.41.dist-info/RECORD
